{
  "version": 6,
  "cmakeMinimumRequired": { "major": 3, "minor": 25, "patch": 0 },
  "configurePresets": [
    {
      "name": "ucrt64-debug",
      "displayName": "UCRT64 Debug (Ninja)",
      "generator": "Ninja",
      "binaryDir": "${sourceDir}/build/ucrt64-debug",
      "cacheVariables": {
        "CMAKE_BUILD_TYPE": "Debug",
        "CMAKE_C_COMPILER": "C:/msys64/ucrt64/bin/gcc.exe",
        "CMAKE_CXX_COMPILER": "C:/msys64/ucrt64/bin/g++.exe",
        "CMAKE_CXX_STANDARD": "23",
        "CMAKE_CXX_STANDARD_REQUIRED": "ON",
        "CMAKE_CXX_EXTENSIONS": "OFF"
      }
    },
    {
      "name": "ucrt64-release",
      "displayName": "UCRT64 Release (Ninja)",
      "generator": "Ninja",
      "binaryDir": "${sourceDir}/build/ucrt64-release",
      "cacheVariables": {
        "CMAKE_BUILD_TYPE": "Release",
        "CMAKE_C_COMPILER": "C:/msys64/ucrt64/bin/gcc.exe",
        "CMAKE_CXX_COMPILER": "C:/msys64/ucrt64/bin/g++.exe",
        "CMAKE_CXX_STANDARD": "23",
        "CMAKE_CXX_STANDARD_REQUIRED": "ON",
        "CMAKE_CXX_EXTENSIONS": "OFF"
      }
    }
  ],
  "buildPresets": [
    { "name": "build-ucrt64-debug", "configurePreset": "ucrt64-debug" },
    { "name": "build-ucrt64-release", "configurePreset": "ucrt64-release" }
  ]
}
